setup.py
ryk_distributions/Binomialdistribution.py
ryk_distributions/Gaussiandistribution.py
ryk_distributions/Generaldistribution.py
ryk_distributions/__init__.py
ryk_distributions.egg-info/PKG-INFO
ryk_distributions.egg-info/SOURCES.txt
ryk_distributions.egg-info/dependency_links.txt
ryk_distributions.egg-info/not-zip-safe
ryk_distributions.egg-info/top_level.txt